purecpp_chuncks_clean/RagPUREAI_chuncks_clean.cpython-311-x86_64-linux-gnu.so
purecpp_chuncks_clean/__init__.py
purecpp_chuncks_clean-1.5.4.dist-info/METADATA
purecpp_chuncks_clean-1.5.4.dist-info/WHEEL
purecpp_chuncks_clean-1.5.4.dist-info/top_level.txt
purecpp_chuncks_clean-1.5.4.dist-info/RECORD
