Metadata-Version: 2.2
Name: purecpp_chuncks_clean
Version: 1.5.4
Summary: Binding de C++ e Python
Author: Seu Nome
Author-email: seu.email@exemplo.com
Classifier: Programming Language :: Python :: 3
Classifier: Operating System :: POSIX :: Linux
Requires-Dist: purecpp_libs
Requires-Dist: auditwheel
Requires-Dist: build
Requires-Dist: requests
Requires-Dist: wheel
Requires-Dist: pybind11
Requires-Dist: setuptools
Dynamic: author
Dynamic: author-email
Dynamic: classifier
Dynamic: requires-dist
Dynamic: summary
